{
  "header": {
    "message_id": 344,
    "timestamp": "2025-10-23T14:45:31.310509Z",
    "source": "EPS_MCU",
    "message_type": "SUMMARY",
    "priority": "MEDIUM",
    "version": "1.0"
  },
  "payload": {
    "rule_triggered": "R4",
    "values": {},
    "ratio": 0.46243681366567896,
    "actions_taken": [
      "REDUCE_LOAD",
      "LED_YELLOW"
    ],
    "emergency_level": "MEDIUM",
    "temporal_window": {
      "window_size_seconds": 30.0,
      "data_points_count": 100,
      "sensor_data": [
        {
          "timestamp": "2025-10-22 20:19:05.230548",
          "V_batt": 8.16,
          "I_batt": 1.186,
          "T_batt": 6.2,
          "V_solar": 17.573,
          "I_solar": 0.874,
          "V_bus": 8.088,
          "I_bus": 0.601,
          "T_eps": 6.8,
          "SOC": 71.0,
          "anomaly_type": "normal",
          "orbit_sunlight": true,
          "P_batt": 9.67776,
          "P_solar": 15.358802,
          "P_bus": 4.860887999999999,
          "converter_ratio": 0.4602515222215899,
          "charge_efficiency": 0.6301116454265117,
          "delta_V_batt": 0.1850000000000005,
          "delta_I_batt": 1.826,
          "delta_T_batt": 14.0,
          "delta_V_bus": 0.1269999999999989,
          "delta_I_bus": 0.005,
          "delta_SOC": 13.1,
          "rolling_std_V_batt": 0.1069049941666169,
          "rolling_mean_V_batt": 8.095699999999999,
          "rolling_std_I_batt": 1.0763265974807297,
          "rolling_mean_I_batt": 1.3195,
          "rolling_std_T_batt": 5.4324641431551415,
          "rolling_mean_T_batt": 5.650000000000001,
          "V_batt_V_bus_ratio": 1.0089020771513355,
          "power_balance": 0.8201540000000023
        },
        {
          "timestamp": "2025-10-22 20:19:22.510548",
          "V_batt": 8.334,
          "I_batt": 2.532,
          "T_batt": 6.8,
          "V_solar": 17.915,
          "I_solar": 1.934,
          "V_bus": 8.199,
          "I_bus": 0.587,
          "T_eps": 7.1,
          "SOC": 81.3,
          "anomaly_type": "normal",
          "orbit_sunlight": true,
          "P_batt": 21.101688,
          "P_solar": 34.64761,
          "P_bus": 4.812812999999999,
          "converter_ratio": 0.4576611777839799,
          "charge_efficiency": 0.6090373333110134,
          "delta_V_batt": 0.1739999999999995,
          "delta_I_batt": 1.346,
          "delta_T_batt": 0.5999999999999996,
          "delta_V_bus": 0.1110000000000006,
          "delta_I_bus": -0.014,
          "delta_SOC": 10.299999999999995,
          "rolling_std_V_batt": 0.1271483822590682,
          "rolling_mean_V_batt": 8.1264,
          "rolling_std_I_batt": 1.0789269566461752,
          "rolling_mean_I_batt": 1.3216,
          "rolling_std_T_batt": 5.301781671182675,
          "rolling_mean_T_batt": 5.400000000000001,
          "V_batt_V_bus_ratio": 1.0164654226125136,
          "power_balance": 8.733109000000002
        },
        {
          "timestamp": "2025-10-22 20:19:39.790548",
          "V_batt": 8.028,
          "I_batt": 2.499,
          "T_batt": 6.6,
          "V_solar": 16.004,
          "I_solar": 1.874,
          "V_bus": 7.875,
          "I_bus": 0.619,
          "T_eps": 8.0,
          "SOC": 62.5,
          "anomaly_type": "normal",
          "orbit_sunlight": true,
          "P_batt": 20.061972,
          "P_solar": 29.991496000000005,
          "P_bus": 4.874625,
          "converter_ratio": 0.4920644838790302,
          "charge_efficiency": 0.6689220170944457,
          "delta_V_batt": -0.3059999999999991,
          "delta_I_batt": -0.0329999999999999,
          "delta_T_batt": -0.2000000000000001,
          "delta_V_bus": -0.3239999999999998,
          "delta_I_bus": 0.032,
          "delta_SOC": -18.8,
          "rolling_std_V_batt": 0.1262371665644047,
          "rolling_mean_V_batt": 8.1274,
          "rolling_std_I_batt": 1.1250918184752745,
          "rolling_mean_I_batt": 1.4846,
          "rolling_std_T_batt": 5.197103894371226,
          "rolling_mean_T_batt": 5.190000000000001,
          "V_batt_V_bus_ratio": 1.0194285714285716,
          "power_balance": 5.054899000000004
        },
        {
          "timestamp": "2025-10-22 20:19:57.070548",
          "V_batt": 8.144,
          "I_batt": 2.485,
          "T_batt": 7.5,
          "V_solar": 15.056,
          "I_solar": 1.948,
          "V_bus": 8.006,
          "I_bus": 0.626,
          "T_eps": 9.0,
          "SOC": 70.0,
          "anomaly_type": "normal",
          "orbit_sunlight": true,
          "P_batt": 20.23784,
          "P_solar": 29.329088,
          "P_bus": 5.011756,
          "converter_ratio": 0.5317481402763019,
          "charge_efficiency": 0.6900262292506334,
          "delta_V_batt": 0.1159999999999996,
          "delta_I_batt": -0.0140000000000002,
          "delta_T_batt": 0.9000000000000004,
          "delta_V_bus": 0.1310000000000002,
          "delta_I_bus": 0.007,
          "delta_SOC": 7.5,
          "rolling_std_V_batt": 0.1228107849045681,
          "rolling_mean_V_batt": 8.1374,
          "rolling_std_I_batt": 1.1479891404829,
          "rolling_mean_I_batt": 1.5122,
          "rolling_std_T_batt": 5.095575422745558,
          "rolling_mean_T_batt": 5.040000000000001,
          "V_batt_V_bus_ratio": 1.017237072195853,
          "power_balance": 4.079492
        },
        {
          "timestamp": "2025-10-22 20:20:14.350548",
          "V_batt": 8.256,
          "I_batt": 2.516,
          "T_batt": 7.5,
          "V_solar": 16.195,
          "I_solar": 1.83,
          "V_bus": 8.141,
          "I_bus": 0.623,
          "T_eps": 8.7,
          "SOC": 76.3,
          "anomaly_type": "normal",
          "orbit_sunlight": true,
          "P_batt": 20.772096,
          "P_solar": 29.636850000000003,
          "P_bus": 5.071843,
          "converter_ratio": 0.5026860142019142,
          "charge_efficiency": 0.7008874424913578,
          "delta_V_batt": 0.1120000000000001,
          "delta_I_batt": 0.0310000000000001,
          "delta_T_batt": 0.0,
          "delta_V_bus": 0.1349999999999998,
          "delta_I_bus": -0.003,
          "delta_SOC": 6.299999999999997,
          "rolling_std_V_batt": 0.1201811595513135,
          "rolling_mean_V_batt": 8.135200000000001,
          "rolling_std_I_batt": 1.1487627160461722,
          "rolling_mean_I_batt": 1.513,
          "rolling_std_T_batt": 4.986971915791043,
          "rolling_mean_T_batt": 4.8900000000000015,
          "V_batt_V_bus_ratio": 1.0141260287433975,
          "power_balance": 3.792911000000001
        },
        {
          "timestamp": "2025-10-22 20:20:31.630548",
          "V_batt": 8.033,
          "I_batt": 1.924,
          "T_batt": 7.1,
          "V_solar": 15.663,
          "I_solar": 1.42,
          "V_bus": 7.92,
          "I_bus": 0.63,
          "T_eps": 8.3,
          "SOC": 62.0,
          "anomaly_type": "normal",
          "orbit_sunlight": true,
          "P_batt": 15.455491999999998,
          "P_solar": 22.24146,
          "P_bus": 4.9896,
          "converter_ratio": 0.505650258571155,
          "charge_efficiency": 0.694895568905998,
          "delta_V_batt": -0.2230000000000007,
          "delta_I_batt": -0.5920000000000001,
          "delta_T_batt": -0.4000000000000003,
          "delta_V_bus": -0.221,
          "delta_I_bus": 0.007,
          "delta_SOC": -14.299999999999995,
          "rolling_std_V_batt": 0.1196768333656572,
          "rolling_mean_V_batt": 8.1161,
          "rolling_std_I_batt": 1.1082040977284928,
          "rolling_mean_I_batt": 1.4561,
          "rolling_std_T_batt": 4.737040801550607,
          "rolling_mean_T_batt": 5.580000000000001,
          "V_batt_V_bus_ratio": 1.0142676767676768,
          "power_balance": 1.796368000000002
        },
        {
          "timestamp": "2025-10-22 20:20:48.910548",
          "V_batt": 8.172,
          "I_batt": 0.314,
          "T_batt": 5.4,
          "V_solar": 15.038,
          "I_solar": 0.548,
          "V_bus": 8.164,
          "I_bus": 0.641,
          "T_eps": 6.7,
          "SOC": 71.6,
          "anomaly_type": "normal",
          "orbit_sunlight": true,
          "P_batt": 2.566008,
          "P_solar": 8.240824,
          "P_bus": 5.233124,
          "converter_ratio": 0.5428913419337678,
          "charge_efficiency": 0.3113776001040673,
          "delta_V_batt": 0.1390000000000011,
          "delta_I_batt": -1.61,
          "delta_T_batt": -1.6999999999999993,
          "delta_V_bus": 0.2439999999999997,
          "delta_I_bus": 0.011,
          "delta_SOC": 9.599999999999994,
          "rolling_std_V_batt": 0.116520146088269,
          "rolling_mean_V_batt": 8.1305,
          "rolling_std_I_batt": 1.1601594717968735,
          "rolling_mean_I_batt": 1.386,
          "rolling_std_T_batt": 4.646862740961153,
          "rolling_mean_T_batt": 5.300000000000002,
          "V_batt_V_bus_ratio": 1.0009799118079374,
          "power_balance": 0.4416919999999997
        },
        {
          "timestamp": "2025-10-22 20:21:06.190548",
          "V_batt": 8.109,
          "I_batt": 2.525,
          "T_batt": 4.2,
          "V_solar": 16.1,
          "I_solar": 1.898,
          "V_bus": 7.976,
          "I_bus": 0.649,
          "T_eps": 6.2,
          "SOC": 67.6,
          "anomaly_type": "normal",
          "orbit_sunlight": true,
          "P_batt": 20.475225,
          "P_solar": 30.5578,
          "P_bus": 5.176424,
          "converter_ratio": 0.4954037267080745,
          "charge_efficiency": 0.6700490545785364,
          "delta_V_batt": -0.0630000000000006,
          "delta_I_batt": 2.211,
          "delta_T_batt": -1.2000000000000002,
          "delta_V_bus": -0.1879999999999997,
          "delta_I_bus": 0.008,
          "delta_SOC": -4.0,
          "rolling_std_V_batt": 0.1145928056690213,
          "rolling_mean_V_batt": 8.122200000000001,
          "rolling_std_I_batt": 1.1654604669399993,
          "rolling_mean_I_batt": 1.5881,
          "rolling_std_T_batt": 4.607240678178898,
          "rolling_mean_T_batt": 5.000000000000002,
          "V_batt_V_bus_ratio": 1.0166750250752257,
          "power_balance": 4.906151000000002
        },
        {
          "timestamp": "2025-10-22 20:21:23.470548",
          "V_batt": 8.268,
          "I_batt": 2.49,
          "T_batt": 3.9,
          "V_solar": 15.904,
          "I_solar": 1.964,
          "V_bus": 8.112,
          "I_bus": 0.648,
          "T_eps": 7.7,
          "SOC": 76.1,
          "anomaly_type": "normal",
          "orbit_sunlight": true,
          "P_batt": 20.58732,
          "P_solar": 31.235456,
          "P_bus": 5.256576,
          "converter_ratio": 0.5100603621730382,
          "charge_efficiency": 0.6591009908739608,
          "delta_V_batt": 0.1590000000000007,
          "delta_I_batt": -0.0349999999999997,
          "delta_T_batt": -0.3000000000000002,
          "delta_V_bus": 0.1360000000000001,
          "delta_I_bus": -0.001,
          "delta_SOC": 8.5,
          "rolling_std_V_batt": 0.1156963938744114,
          "rolling_mean_V_batt": 8.147900000000002,
          "rolling_std_I_batt": 1.1333011220912714,
          "rolling_mean_I_batt": 1.7831000000000004,
          "rolling_std_T_batt": 4.586501935026267,
          "rolling_mean_T_batt": 4.740000000000002,
          "V_batt_V_bus_ratio": 1.0192307692307694,
          "power_balance": 5.3915599999999975
        },
        {
          "timestamp": "2025-10-22 20:21:40.750548",
          "V_batt": 8.048,
          "I_batt": 1.004,
          "T_batt": 4.7,
          "V_solar": 17.211,
          "I_solar": 0.826,
          "V_bus": 7.959,
          "I_bus": 0.657,
          "T_eps": 8.0,
          "SOC": 62.6,
          "anomaly_type": "normal",
          "orbit_sunlight": true,
          "P_batt": 8.080192,
          "P_solar": 14.216285999999998,
          "P_bus": 5.229063,
          "converter_ratio": 0.4624368136656789,
          "charge_efficiency": 0.5683757347031426,
          "delta_V_batt": -0.2200000000000006,
          "delta_I_batt": -1.4860000000000002,
          "delta_T_batt": 0.8000000000000003,
          "delta_V_bus": -0.1530000000000004,
          "delta_I_bus": 0.009,
          "delta_SOC": -13.499999999999991,
          "rolling_std_V_batt": 0.1054216928972439,
          "rolling_mean_V_batt": 8.155199999999999,
          "rolling_std_I_batt": 0.8181722516275749,
          "rolling_mean_I_batt": 1.9475,
          "rolling_std_T_batt": 1.3519122259474932,
          "rolling_mean_T_batt": 5.990000000000001,
          "V_batt_V_bus_ratio": 1.0111823093353436,
          "power_balance": 0.907030999999998
        }
      ]
    }
  }
}